stageflow/__init__.py
stageflow/core.py
stageflow/panda3d.py
stageflow/prefab.py
stageflow/wecs.py
panda3d_stageflow-0.1b4.dist-info/LICENSE
panda3d_stageflow-0.1b4.dist-info/METADATA
panda3d_stageflow-0.1b4.dist-info/WHEEL
panda3d_stageflow-0.1b4.dist-info/top_level.txt
panda3d_stageflow-0.1b4.dist-info/RECORD
