Metadata-Version: 2.1
Name: panda3d-stageflow
Version: 0.1b4
Summary: A kind of FSM for game states
Home-page: https://github.com/TheCheapestPixels/panda3d-stageflow/
Author: TheCheapestPixels
Author-email: TheCheapestPixels@gmail.com
License: UNKNOWN
Keywords: stageflow panda3d
Platform: UNKNOWN
Classifier: Development Status :: 4 - Beta
Classifier: Intended Audience :: Developers
Classifier: Programming Language :: Python :: 3.7
Requires-Python: >=3.5, <4
